projects/vga/camera/i2c.v
module i2c (
    input meg25, // 25MHz
    input[23:0] send_dat,
    input sendit,
    input reset,
    inout sda,
    output scl,
    output ack, //1 when byte send unsuccesful
    output done,
    output [6:0] send_count_out
);
parameter i2c_address = 7'h78; //0x78 for write address
reg done_reg;
reg ack_reg;
reg sda_clk; // put data out on posedge of this
reg scl_clk; //pulses in between sda_clk
reg[5:0] send_count;
reg sda_reg;
reg scl_reg;
assign sda = sda_reg? 1'b1 : 1'b0; //pullup on resistor, change z to 1 to test
//always @(*) begin
    //if (6'd38 < send_count < 6'd2) begin
        //scl = scl_reg;
    //end else begin
        //scl = scl_clk;
    //end
//end
assign scl = ( (6'd2 > send_count) | (send_count > 6'd38) )?scl_reg:scl_clk;


assign done = done_reg;
assign ack = ack_reg;

initial begin
    sda_clk = 1'b0;
    scl_clk = 1'b0;
    clk_count = 7'd0;
    send_count = 6'd0;
    done_reg = 1'b0;
    sda_reg = 1'b1;
    scl_reg = 1'b1;
end

assign send_count_out = send_count; //for testing

reg[6:0] clk_count;
always @(posedge meg25) begin //create main timing
    if(clk_count < 7'd125) begin
     clk_count = clk_count + 1'b1;
    end else begin
        clk_count = 7'd0;
    end
    if(clk_count == 7'd62) begin
        sda_clk <= 1'b1;
    end
    if(clk_count == 7'd72) begin
       scl_clk <= 1'b1;
    end
    if(clk_count == 7'd115) begin
      scl_clk <= 1'b0;
    end
    if(clk_count == 7'd0) begin
       sda_clk <= 1'b0; 
    end
end

always @(posedge scl_clk or negedge scl_clk or posedge reset) begin
    if (reset) begin
        ack_reg <= 1'b0;
    end else begin
        if (send_count == 6'd11 | 6'd20 | 6'd29 | 6'd38) begin
            ack_reg <= (ack_reg | sda);
        end
    end
end

always @(negedge sda_clk) begin
    if (send_count < 6'd41) begin
        send_count <= send_count + 1'b1;
    end else begin
        send_count <= 6'd0;
    end
end
always @(posedge sda_clk or posedge reset) begin
    if(reset) begin
        send_count <= 6'd0;
    end else begin
        if(sendit) begin
            case(send_count)
                0: begin
                    sda_reg <= 1'b0;
                    scl_reg <= 1'b1;
                    done_reg = 1'b0;
                end
                1: begin
                    sda_reg <= 1'b0;
                    scl_reg <= 1'b0;
                end
                2: begin
                    sda_reg <= 1'b0;
                    scl_reg <= 1'b0;
                end
                3:sda_reg <= i2c_address[6];
                4:sda_reg <= i2c_address[5];
                5:sda_reg <= i2c_address[4];
                6:sda_reg <= i2c_address[3];
                7:sda_reg <= i2c_address[2];
                8:sda_reg <= i2c_address[1];
                9:sda_reg <= i2c_address[0];
                10:sda_reg <= 1'b0; //skip 11, ack bit
                12:sda_reg <= send_dat[23];
                13:sda_reg <= send_dat[22];
                14:sda_reg <= send_dat[21];
                15:sda_reg <= send_dat[20];
                16:sda_reg <= send_dat[19];
                17:sda_reg <= send_dat[18];
                18:sda_reg <= send_dat[17];
                19:sda_reg <= send_dat[16]; //skip 20, ack bit
                21:sda_reg <= send_dat[15];
                22:sda_reg <= send_dat[14];
                23:sda_reg <= send_dat[13];
                24:sda_reg <= send_dat[12];
                25:sda_reg <= send_dat[11];
                26:sda_reg <= send_dat[10];
                27:sda_reg <= send_dat[9];
                28:sda_reg <= send_dat[8]; //skip 29, ack bit
                30:sda_reg <= send_dat[7];
                31:sda_reg <= send_dat[6];
                32:sda_reg <= send_dat[5];
                33:sda_reg <= send_dat[4];
                34:sda_reg <= send_dat[3];
                35:sda_reg <= send_dat[2];
                36:sda_reg <= send_dat[1];
                37:sda_reg <= send_dat[0]; //skip 38, ack bit
                39:sda_reg <= 1'b0;
                40:scl_reg <= 1'b1;
                41:begin 
                    sda_reg <= 1'b1;
                    done_reg <= 1'b1;
                end
                endcase

        end else begin //if sendit == 0;
            send_count <= 6'd0;
            done_reg <= 1'b0;
            sda_reg <= 1'b1;
            scl_reg <= 1'b1;
        end
    end
end

endmodule

projects/vga/camera/i2c_tb.v
module i2c_tb ();

wire done;
wire meg25;
wire sda;
wire scl;
wire ack;
wire[23:0] send_dat;
wire [6:0] send_count;
reg sendit;
reg meg_reg25;
assign meg25 = meg_reg25;
assign send_dat = 24'b111111111111111111111111;
i2c dude (.scl(scl), .sda(sda), .meg25(meg25), .send_dat(send_dat), .sendit(sendit), .send_count_out(send_count), .ack(ack), .done(done));

initial begin
$dumpfile("test.vcd");
$dumpvars(0, sda, scl, sendit, send_count, ack, done);
meg_reg25 = 1'b0;
sendit = 1'b0;
#2000 sendit = 1'b1;
#25000;
$finish;
end

always begin
    #1 meg_reg25 = ~meg_reg25;
end

always @(done) begin
    if(done) begin
        sendit = 1'b0;
    end else begin
        #2000 sendit = 1'b1;
    end
end
endmodule

projects/vga/camera/test.vcd
$date
	Sat Feb  1 11:42:50 2025
$end
$version
	Icarus Verilog
$end
$timescale
	1s
$end
$scope module i2c_tb $end
$var wire 1 ! sda $end
$upscope $end
$scope module i2c_tb $end
$var wire 1 " scl $end
$upscope $end
$scope module i2c_tb $end
$var reg 1 # sendit $end
$upscope $end
$scope module i2c_tb $end
$var wire 7 $ send_count [6:0] $end
$upscope $end
$enddefinitions $end
$comment Show the parameter values. $end
$dumpall
$end
#0
$dumpvars
b0 $
x#
1"
1!
$end
#10
1#
#123
0!
#251
b1 $
#375
0"
#503
b10 $
#647
1"
#733
0"
#755
b11 $
#879
1!
#899
1"
#985
0"
#1007
b100 $
#1151
1"
#1237
0"
#1259
b101 $
#1403
1"
#1489
0"
#1511
b110 $
#1655
1"
#1741
0"
#1763
b111 $
#1887
0!
#1907
1"
#1993
0"
#2015
b1000 $
#2159
1"
#2245
0"
#2267
b1001 $
#2411
1"
#2497
0"
#2519
b1010 $
#2663
1"
#2749
0"
#2771
b1011 $
#2915
1"
#3001
0"
#3023
b1100 $
#3147
1!
#3167
1"
#3253
0"
#3275
b1101 $
#3419
1"
#3505
0"
#3527
b1110 $
#3671
1"
#3757
0"
#3779
b1111 $
#3923
1"
#4009
0"
#4031
b10000 $
#4175
1"
#4261
0"
#4283
b10001 $
#4427
1"
#4513
0"
#4535
b10010 $
#4679
1"
#4765
0"
#4787
b10011 $
#4931
1"
#5017
0"
#5039
b10100 $
#5183
1"
#5269
0"
#5291
b10101 $
#5435
1"
#5521
0"
#5543
b10110 $
#5687
1"
#5773
0"
#5795
b10111 $
#5939
1"
#6025
0"
#6047
b11000 $
#6191
1"
#6277
0"
#6299
b11001 $
#6443
1"
#6529
0"
#6551
b11010 $
#6695
1"
#6781
0"
#6803
b11011 $
#6947
1"
#7033
0"
#7055
b11100 $
#7199
1"
#7285
0"
#7307
b11101 $
#7451
1"
#7537
0"
#7559
b11110 $
#7703
1"
#7789
0"
#7811
b11111 $
#7955
1"
#8041
0"
#8063
b100000 $
#8207
1"
#8293
0"
#8315
b100001 $
#8459
1"
#8545
0"
#8567
b100010 $
#8711
1"
#8797
0"
#8819
b100011 $
#8963
1"
#9049
0"
#9071
b100100 $
#9215
1"
#9301
0"
#9323
b100101 $
#9467
1"
#9553
0"
#9575
b100110 $
#9719
1"
#9805
0"
#9827
b100111 $
#9951
0!
#10079
b101000 $
#10203
1"
#10331
b101001 $
#10455
1!
#10583
b0 $
#10707
0!
#10835
b1 $
#10959
0"
#11087
b10 $
#11231
1"
#11317
0"
#11339
b11 $
#11463
1!
#11483
1"
#11569
0"
#11591
b100 $
#11735
1"
#11821
0"
#11843
b101 $
#11987
1"
#12073
0"
#12095
b110 $
#12239
1"
#12325
0"
#12347
b111 $
#12471
0!
#12491
1"
#12577
0"
#12599
b1000 $
#12743
1"
#12829
0"
#12851
b1001 $
#12995
1"
#13081
0"
#13103
b1010 $
#13247
1"
#13333
0"
#13355
b1011 $
#13499
1"
#13585
0"
#13607
b1100 $
#13731
1!
#13751
1"
#13837
0"
#13859
b1101 $
#14003
1"
#14089
0"
#14111
b1110 $
#14255
1"
#14341
0"
#14363
b1111 $
#14507
1"
#14593
0"
#14615
b10000 $
#14759
1"
#14845
0"
#14867
b10001 $
